{
  "$schema": "https://developer.microsoft.com/json-schemas/fabric/item/report/definition/visualContainer/2.4.0/schema.json",
  "name": "45e4721b02e015047ed2",
  "position": {
    "x": 4.7302291204730222,
    "y": 107.84922394678492,
    "z": 0,
    "height": 605.46932742054685,
    "width": 1077.5461936437546,
    "tabOrder": 3000
  },
  "visual": {
    "visualType": "ribbonChart",
    "query": {
      "queryState": {
        "Category": {
          "projections": [
            {
              "field": {
                "HierarchyLevel": {
                  "Expression": {
                    "Hierarchy": {
                      "Expression": {
                        "SourceRef": {
                          "Entity": "D_Date"
                        }
                      },
                      "Hierarchy": "DayOfMonth Hierarchy"
                    }
                  },
                  "Level": "Year"
                }
              },
              "queryRef": "DateTable.DayOfMonth Hierarchy.Year",
              "nativeQueryRef": "DayOfMonth Hierarchy Year",
              "active": true
            },
            {
              "field": {
                "HierarchyLevel": {
                  "Expression": {
                    "Hierarchy": {
                      "Expression": {
                        "SourceRef": {
                          "Entity": "D_Date"
                        }
                      },
                      "Hierarchy": "DayOfMonth Hierarchy"
                    }
                  },
                  "Level": "Quarter"
                }
              },
              "queryRef": "DateTable.DayOfMonth Hierarchy.Quarter",
              "nativeQueryRef": "DayOfMonth Hierarchy Quarter",
              "active": true
            },
            {
              "field": {
                "HierarchyLevel": {
                  "Expression": {
                    "Hierarchy": {
                      "Expression": {
                        "SourceRef": {
                          "Entity": "D_Date"
                        }
                      },
                      "Hierarchy": "DayOfMonth Hierarchy"
                    }
                  },
                  "Level": "MonthShort"
                }
              },
              "queryRef": "DateTable.DayOfMonth Hierarchy.MonthShort",
              "nativeQueryRef": "DayOfMonth Hierarchy MonthShort",
              "active": true
            },
            {
              "field": {
                "HierarchyLevel": {
                  "Expression": {
                    "Hierarchy": {
                      "Expression": {
                        "SourceRef": {
                          "Entity": "D_Date"
                        }
                      },
                      "Hierarchy": "DayOfMonth Hierarchy"
                    }
                  },
                  "Level": "Day of Month"
                }
              },
              "queryRef": "DateTable.DayOfMonth Hierarchy.DayOfMonth",
              "nativeQueryRef": "DayOfMonth Hierarchy DayOfMonth",
              "active": false
            },
            {
              "field": {
                "Column": {
                  "Expression": {
                    "SourceRef": {
                      "Entity": "D_Time"
                    }
                  },
                  "Property": "Hour"
                }
              },
              "queryRef": "DayTimeTable.Hour",
              "nativeQueryRef": "Hour",
              "active": false
            }
          ]
        },
        "Series": {
          "projections": [
            {
              "field": {
                "Column": {
                  "Expression": {
                    "SourceRef": {
                      "Entity": "D_Location"
                    }
                  },
                  "Property": "Location"
                }
              },
              "queryRef": "location_data.location_name",
              "nativeQueryRef": "location_name"
            }
          ]
        },
        "Y": {
          "projections": [
            {
              "field": {
                "Measure": {
                  "Expression": {
                    "SourceRef": {
                      "Entity": "Main_Measures"
                    }
                  },
                  "Property": "Sales Aggregation"
                }
              },
              "queryRef": "HourlyMeasureDefinitions.SelectedAtomicMeasure",
              "nativeQueryRef": "SelectedAtomicMeasure"
            }
          ]
        }
      }
    },
    "objects": {
      "legend": [
        {
          "properties": {
            "showGradientLegend": {
              "expr": {
                "Literal": {
                  "Value": "true"
                }
              }
            },
            "show": {
              "expr": {
                "Literal": {
                  "Value": "true"
                }
              }
            }
          }
        }
      ],
      "valueAxis": [
        {
          "properties": {
            "gridlineThickness": {
              "expr": {
                "Literal": {
                  "Value": "3D"
                }
              }
            },
            "gridlineColor": {
              "solid": {
                "color": {
                  "expr": {
                    "ThemeDataColor": {
                      "ColorId": 1,
                      "Percent": 0.6
                    }
                  }
                }
              }
            }
          }
        }
      ],
      "categoryAxis": [
        {
          "properties": {
            "gridlineThickness": {
              "expr": {
                "Literal": {
                  "Value": "3D"
                }
              }
            },
            "gridlineAutoScale": {
              "expr": {
                "Literal": {
                  "Value": "false"
                }
              }
            },
            "gridlineColor": {
              "solid": {
                "color": {
                  "expr": {
                    "ThemeDataColor": {
                      "ColorId": 1,
                      "Percent": 0.6
                    }
                  }
                }
              }
            }
          }
        }
      ]
    },
    "drillFilterOtherVisuals": true
  }
}