{
  "$schema": "https://developer.microsoft.com/json-schemas/fabric/item/report/definition/bookmark/1.4.0/schema.json",
  "displayName": "Temporal First",
  "name": "9706fdbc9af83aa85b20",
  "options": {
    "applyOnlyToTargetVisuals": true,
    "targetVisualNames": [
      "43064a0a78d1a573e795",
      "99f3ef13711380cedae1",
      "b4ec5de1d8476c1cc142",
      "2660c802ad751abc5be7",
      "ba13c66ee07617c6005d",
      "4ac5d17042a0ac499950",
      "b0abf288d958e14598fa",
      "00755717c1dabf254908",
      "454348e12d64ed65119d",
      "ad5afa81b9ab2b4c2140"
    ]
  },
  "explorationState": {
    "version": "1.3",
    "activeSection": "2a609ba74b8ab7a3b008",
    "filters": {
      "byExpr": [
        {
          "name": "cabc571d9ff313746c59",
          "type": "Categorical",
          "filter": {
            "Version": 2,
            "From": [
              {
                "Name": "d",
                "Entity": "D_Date",
                "Type": 0
              }
            ],
            "Where": [
              {
                "Condition": {
                  "In": {
                    "Expressions": [
                      {
                        "Column": {
                          "Expression": {
                            "SourceRef": {
                              "Source": "d"
                            }
                          },
                          "Property": "IsActive"
                        }
                      }
                    ],
                    "Values": [
                      [
                        {
                          "Literal": {
                            "Value": "1L"
                          }
                        }
                      ]
                    ]
                  }
                }
              }
            ]
          },
          "expression": {
            "Column": {
              "Expression": {
                "SourceRef": {
                  "Entity": "D_Date"
                }
              },
              "Property": "IsActive"
            }
          },
          "howCreated": 1
        }
      ]
    },
    "sections": {
      "2a609ba74b8ab7a3b008": {
        "filters": {
          "byExpr": [
            {
              "name": "6682e01032ed82cc9559",
              "type": "Categorical",
              "filter": {
                "Version": 2,
                "From": [
                  {
                    "Name": "l",
                    "Entity": "D_Location",
                    "Type": 0
                  }
                ],
                "Where": [
                  {
                    "Condition": {
                      "In": {
                        "Expressions": [
                          {
                            "Column": {
                              "Expression": {
                                "SourceRef": {
                                  "Source": "l"
                                }
                              },
                              "Property": "Location"
                            }
                          }
                        ],
                        "Values": [
                          [
                            {
                              "Literal": {
                                "Value": "'Turku'"
                              }
                            }
                          ]
                        ]
                      }
                    }
                  }
                ]
              },
              "expression": {
                "Column": {
                  "Expression": {
                    "SourceRef": {
                      "Entity": "D_Location"
                    }
                  },
                  "Property": "Location"
                }
              },
              "howCreated": 5
            }
          ]
        },
        "visualContainers": {
          "d5a2ae435e5d1509caa0": {
            "filters": {
              "byExpr": [
                {
                  "name": "d76ffdae509d4ddb2a31",
                  "type": "Advanced",
                  "expression": {
                    "Measure": {
                      "Expression": {
                        "SourceRef": {
                          "Entity": "Support_Measures"
                        }
                      },
                      "Property": "Drill Through Title Location"
                    }
                  },
                  "howCreated": 0
                }
              ]
            },
            "singleVisual": {
              "visualType": "card",
              "objects": {}
            }
          },
          "49dc38fd49015a70295d": {
            "filters": {
              "byExpr": [
                {
                  "name": "90f219136f68dd2cf6e5",
                  "type": "Categorical",
                  "expression": {
                    "Column": {
                      "Expression": {
                        "SourceRef": {
                          "Entity": "D_Salesperson"
                        }
                      },
                      "Property": "Name"
                    }
                  },
                  "howCreated": 0
                },
                {
                  "name": "1e253db74c386465488d",
                  "type": "Advanced",
                  "expression": {
                    "Measure": {
                      "Expression": {
                        "SourceRef": {
                          "Entity": "Main_Measures"
                        }
                      },
                      "Property": "Sales Aggregation"
                    }
                  },
                  "howCreated": 0
                }
              ]
            },
            "singleVisual": {
              "visualType": "tableEx",
              "objects": {}
            }
          },
          "00755717c1dabf254908": {
            "filters": {
              "byExpr": [
                {
                  "name": "9526a10a4b88d692e503",
                  "type": "Categorical",
                  "expression": {
                    "Column": {
                      "Expression": {
                        "SourceRef": {
                          "Entity": "HourAggregation"
                        }
                      },
                      "Property": "Hour Aggregation"
                    }
                  },
                  "howCreated": 0
                }
              ]
            },
            "singleVisual": {
              "visualType": "slicer",
              "objects": {
                "merge": {
                  "general": [
                    {
                      "properties": {
                        "filter": {
                          "filter": {
                            "Version": 2,
                            "From": [
                              {
                                "Name": "h",
                                "Entity": "HourAggregation",
                                "Type": 0
                              }
                            ],
                            "Where": [
                              {
                                "Condition": {
                                  "In": {
                                    "Expressions": [
                                      {
                                        "Column": {
                                          "Expression": {
                                            "SourceRef": {
                                              "Source": "h"
                                            }
                                          },
                                          "Property": "Hour Aggregation"
                                        }
                                      }
                                    ],
                                    "Values": [
                                      [
                                        {
                                          "Literal": {
                                            "Value": "'None'"
                                          }
                                        }
                                      ]
                                    ]
                                  }
                                }
                              }
                            ]
                          }
                        }
                      }
                    }
                  ],
                  "data": [
                    {
                      "properties": {
                        "mode": {
                          "expr": {
                            "Literal": {
                              "Value": "'Dropdown'"
                            }
                          }
                        }
                      }
                    }
                  ],
                  "selection": [
                    {
                      "properties": {
                        "strictSingleSelect": {
                          "expr": {
                            "Literal": {
                              "Value": "true"
                            }
                          }
                        }
                      }
                    }
                  ]
                }
              },
              "activeProjections": {
                "Values": [
                  {
                    "Column": {
                      "Expression": {
                        "SourceRef": {
                          "Entity": "HourAggregation"
                        }
                      },
                      "Property": "Hour Aggregation"
                    }
                  }
                ]
              },
              "display": {
                "mode": "hidden"
              }
            }
          },
          "2660c802ad751abc5be7": {
            "filters": {
              "byExpr": [
                {
                  "name": "2edc98867bdbb2777842",
                  "type": "Categorical",
                  "expression": {
                    "Column": {
                      "Expression": {
                        "SourceRef": {
                          "Entity": "HourAggregationTemporalFirst"
                        }
                      },
                      "Property": "Hour Aggregation"
                    }
                  },
                  "howCreated": 0
                }
              ]
            },
            "singleVisual": {
              "visualType": "slicer",
              "objects": {
                "merge": {
                  "general": [
                    {
                      "properties": {
                        "filter": {
                          "filter": {
                            "Version": 2,
                            "From": [
                              {
                                "Name": "h",
                                "Entity": "HourAggregationTemporalFirst",
                                "Type": 0
                              }
                            ],
                            "Where": [
                              {
                                "Condition": {
                                  "In": {
                                    "Expressions": [
                                      {
                                        "Column": {
                                          "Expression": {
                                            "SourceRef": {
                                              "Source": "h"
                                            }
                                          },
                                          "Property": "Hour Aggregation"
                                        }
                                      }
                                    ],
                                    "Values": [
                                      [
                                        {
                                          "Literal": {
                                            "Value": "'None'"
                                          }
                                        }
                                      ]
                                    ]
                                  }
                                }
                              }
                            ]
                          }
                        }
                      }
                    }
                  ],
                  "data": [
                    {
                      "properties": {
                        "mode": {
                          "expr": {
                            "Literal": {
                              "Value": "'Dropdown'"
                            }
                          }
                        }
                      }
                    }
                  ],
                  "selection": [
                    {
                      "properties": {
                        "strictSingleSelect": {
                          "expr": {
                            "Literal": {
                              "Value": "true"
                            }
                          }
                        }
                      }
                    }
                  ]
                }
              },
              "activeProjections": {
                "Values": [
                  {
                    "Column": {
                      "Expression": {
                        "SourceRef": {
                          "Entity": "HourAggregationTemporalFirst"
                        }
                      },
                      "Property": "Hour Aggregation"
                    }
                  }
                ]
              }
            }
          },
          "41f7e7e9a9baadba3613": {
            "singleVisual": {
              "visualType": "shape",
              "objects": {}
            }
          },
          "43064a0a78d1a573e795": {
            "filters": {
              "byExpr": [
                {
                  "name": "49a32cb092d8a3e82c45",
                  "type": "Categorical",
                  "expression": {
                    "Column": {
                      "Expression": {
                        "SourceRef": {
                          "Entity": "PersonAggregationTemporalFirst"
                        }
                      },
                      "Property": "Person Aggregation"
                    }
                  },
                  "howCreated": 0
                }
              ]
            },
            "singleVisual": {
              "visualType": "slicer",
              "objects": {
                "merge": {
                  "general": [
                    {
                      "properties": {
                        "filter": {
                          "filter": {
                            "Version": 2,
                            "From": [
                              {
                                "Name": "p",
                                "Entity": "PersonAggregationTemporalFirst",
                                "Type": 0
                              }
                            ],
                            "Where": [
                              {
                                "Condition": {
                                  "In": {
                                    "Expressions": [
                                      {
                                        "Column": {
                                          "Expression": {
                                            "SourceRef": {
                                              "Source": "p"
                                            }
                                          },
                                          "Property": "Person Aggregation"
                                        }
                                      }
                                    ],
                                    "Values": [
                                      [
                                        {
                                          "Literal": {
                                            "Value": "'None'"
                                          }
                                        }
                                      ]
                                    ]
                                  }
                                }
                              }
                            ]
                          }
                        }
                      }
                    }
                  ],
                  "data": [
                    {
                      "properties": {
                        "mode": {
                          "expr": {
                            "Literal": {
                              "Value": "'Dropdown'"
                            }
                          }
                        }
                      }
                    }
                  ],
                  "selection": [
                    {
                      "properties": {
                        "strictSingleSelect": {
                          "expr": {
                            "Literal": {
                              "Value": "true"
                            }
                          }
                        }
                      }
                    }
                  ]
                }
              },
              "activeProjections": {
                "Values": [
                  {
                    "Column": {
                      "Expression": {
                        "SourceRef": {
                          "Entity": "PersonAggregationTemporalFirst"
                        }
                      },
                      "Property": "Person Aggregation"
                    }
                  }
                ]
              }
            }
          },
          "454348e12d64ed65119d": {
            "filters": {
              "byExpr": [
                {
                  "name": "628d28f9db335daa2805",
                  "type": "Categorical",
                  "expression": {
                    "Column": {
                      "Expression": {
                        "SourceRef": {
                          "Entity": "PersonAggregation"
                        }
                      },
                      "Property": "Person Aggregation"
                    }
                  },
                  "howCreated": 0
                }
              ]
            },
            "singleVisual": {
              "visualType": "slicer",
              "objects": {
                "merge": {
                  "general": [
                    {
                      "properties": {
                        "filter": {
                          "filter": {
                            "Version": 2,
                            "From": [
                              {
                                "Name": "p",
                                "Entity": "PersonAggregation",
                                "Type": 0
                              }
                            ],
                            "Where": [
                              {
                                "Condition": {
                                  "In": {
                                    "Expressions": [
                                      {
                                        "Column": {
                                          "Expression": {
                                            "SourceRef": {
                                              "Source": "p"
                                            }
                                          },
                                          "Property": "Person Aggregation"
                                        }
                                      }
                                    ],
                                    "Values": [
                                      [
                                        {
                                          "Literal": {
                                            "Value": "'None'"
                                          }
                                        }
                                      ]
                                    ]
                                  }
                                }
                              }
                            ]
                          }
                        }
                      }
                    }
                  ],
                  "data": [
                    {
                      "properties": {
                        "mode": {
                          "expr": {
                            "Literal": {
                              "Value": "'Dropdown'"
                            }
                          }
                        }
                      }
                    }
                  ],
                  "selection": [
                    {
                      "properties": {
                        "strictSingleSelect": {
                          "expr": {
                            "Literal": {
                              "Value": "true"
                            }
                          }
                        }
                      }
                    }
                  ]
                }
              },
              "activeProjections": {
                "Values": [
                  {
                    "Column": {
                      "Expression": {
                        "SourceRef": {
                          "Entity": "PersonAggregation"
                        }
                      },
                      "Property": "Person Aggregation"
                    }
                  }
                ]
              },
              "display": {
                "mode": "hidden"
              }
            }
          },
          "4ac5d17042a0ac499950": {
            "filters": {
              "byExpr": [
                {
                  "name": "0db773f36bef02704ea6",
                  "type": "Categorical",
                  "expression": {
                    "Column": {
                      "Expression": {
                        "SourceRef": {
                          "Entity": "WeatherIndexAggregation"
                        }
                      },
                      "Property": "Weather Index Aggregation"
                    }
                  },
                  "howCreated": 0
                }
              ]
            },
            "singleVisual": {
              "visualType": "slicer",
              "objects": {
                "merge": {
                  "general": [
                    {
                      "properties": {
                        "filter": {
                          "filter": {
                            "Version": 2,
                            "From": [
                              {
                                "Name": "w",
                                "Entity": "WeatherIndexAggregation",
                                "Type": 0
                              }
                            ],
                            "Where": [
                              {
                                "Condition": {
                                  "In": {
                                    "Expressions": [
                                      {
                                        "Column": {
                                          "Expression": {
                                            "SourceRef": {
                                              "Source": "w"
                                            }
                                          },
                                          "Property": "Weather Index Aggregation"
                                        }
                                      }
                                    ],
                                    "Values": [
                                      [
                                        {
                                          "Literal": {
                                            "Value": "'None'"
                                          }
                                        }
                                      ]
                                    ]
                                  }
                                }
                              }
                            ]
                          }
                        }
                      }
                    }
                  ],
                  "data": [
                    {
                      "properties": {
                        "mode": {
                          "expr": {
                            "Literal": {
                              "Value": "'Dropdown'"
                            }
                          }
                        }
                      }
                    }
                  ],
                  "selection": [
                    {
                      "properties": {
                        "strictSingleSelect": {
                          "expr": {
                            "Literal": {
                              "Value": "true"
                            }
                          }
                        }
                      }
                    }
                  ]
                }
              },
              "activeProjections": {
                "Values": [
                  {
                    "Column": {
                      "Expression": {
                        "SourceRef": {
                          "Entity": "WeatherIndexAggregation"
                        }
                      },
                      "Property": "Weather Index Aggregation"
                    }
                  }
                ]
              },
              "display": {
                "mode": "hidden"
              }
            }
          },
          "4b2a4318d2724a46aa15": {
            "singleVisual": {
              "visualType": "bookmarkNavigator",
              "objects": {}
            }
          },
          "87144e02d6a0c1a6578f": {
            "singleVisual": {
              "visualType": "actionButton",
              "objects": {}
            }
          },
          "99f3ef13711380cedae1": {
            "filters": {
              "byExpr": [
                {
                  "name": "fa03159f0d59fe26afe0",
                  "type": "Categorical",
                  "expression": {
                    "Column": {
                      "Expression": {
                        "SourceRef": {
                          "Entity": "ProductAggregationTemporalFirst"
                        }
                      },
                      "Property": "Product Aggregation"
                    }
                  },
                  "howCreated": 0
                }
              ]
            },
            "singleVisual": {
              "visualType": "slicer",
              "objects": {
                "merge": {
                  "general": [
                    {
                      "properties": {
                        "filter": {
                          "filter": {
                            "Version": 2,
                            "From": [
                              {
                                "Name": "p",
                                "Entity": "ProductAggregationTemporalFirst",
                                "Type": 0
                              }
                            ],
                            "Where": [
                              {
                                "Condition": {
                                  "In": {
                                    "Expressions": [
                                      {
                                        "Column": {
                                          "Expression": {
                                            "SourceRef": {
                                              "Source": "p"
                                            }
                                          },
                                          "Property": "Product Aggregation"
                                        }
                                      }
                                    ],
                                    "Values": [
                                      [
                                        {
                                          "Literal": {
                                            "Value": "'None'"
                                          }
                                        }
                                      ]
                                    ]
                                  }
                                }
                              }
                            ]
                          }
                        }
                      }
                    }
                  ],
                  "data": [
                    {
                      "properties": {
                        "mode": {
                          "expr": {
                            "Literal": {
                              "Value": "'Dropdown'"
                            }
                          }
                        }
                      }
                    }
                  ],
                  "selection": [
                    {
                      "properties": {
                        "strictSingleSelect": {
                          "expr": {
                            "Literal": {
                              "Value": "true"
                            }
                          }
                        }
                      }
                    }
                  ]
                }
              },
              "activeProjections": {
                "Values": [
                  {
                    "Column": {
                      "Expression": {
                        "SourceRef": {
                          "Entity": "ProductAggregationTemporalFirst"
                        }
                      },
                      "Property": "Product Aggregation"
                    }
                  }
                ]
              }
            }
          },
          "ad5afa81b9ab2b4c2140": {
            "filters": {
              "byExpr": [
                {
                  "name": "24f2b39e48ea8dea5d3b",
                  "type": "Categorical",
                  "expression": {
                    "Column": {
                      "Expression": {
                        "SourceRef": {
                          "Entity": "ProductAggregation"
                        }
                      },
                      "Property": "Product Aggregation"
                    }
                  },
                  "howCreated": 0
                }
              ]
            },
            "singleVisual": {
              "visualType": "slicer",
              "objects": {
                "merge": {
                  "general": [
                    {
                      "properties": {
                        "filter": {
                          "filter": {
                            "Version": 2,
                            "From": [
                              {
                                "Name": "p",
                                "Entity": "ProductAggregation",
                                "Type": 0
                              }
                            ],
                            "Where": [
                              {
                                "Condition": {
                                  "In": {
                                    "Expressions": [
                                      {
                                        "Column": {
                                          "Expression": {
                                            "SourceRef": {
                                              "Source": "p"
                                            }
                                          },
                                          "Property": "Product Aggregation"
                                        }
                                      }
                                    ],
                                    "Values": [
                                      [
                                        {
                                          "Literal": {
                                            "Value": "'None'"
                                          }
                                        }
                                      ]
                                    ]
                                  }
                                }
                              }
                            ]
                          }
                        }
                      }
                    }
                  ],
                  "data": [
                    {
                      "properties": {
                        "mode": {
                          "expr": {
                            "Literal": {
                              "Value": "'Dropdown'"
                            }
                          }
                        }
                      }
                    }
                  ],
                  "selection": [
                    {
                      "properties": {
                        "strictSingleSelect": {
                          "expr": {
                            "Literal": {
                              "Value": "true"
                            }
                          }
                        }
                      }
                    }
                  ]
                }
              },
              "activeProjections": {
                "Values": [
                  {
                    "Column": {
                      "Expression": {
                        "SourceRef": {
                          "Entity": "ProductAggregation"
                        }
                      },
                      "Property": "Product Aggregation"
                    }
                  }
                ]
              },
              "display": {
                "mode": "hidden"
              }
            }
          },
          "b0abf288d958e14598fa": {
            "filters": {
              "byExpr": [
                {
                  "name": "3278651ff96922098a0b",
                  "type": "Categorical",
                  "expression": {
                    "Column": {
                      "Expression": {
                        "SourceRef": {
                          "Entity": "DateAggregation"
                        }
                      },
                      "Property": "Date Aggregation"
                    }
                  },
                  "howCreated": 0
                }
              ]
            },
            "singleVisual": {
              "visualType": "slicer",
              "objects": {
                "merge": {
                  "general": [
                    {
                      "properties": {
                        "filter": {
                          "filter": {
                            "Version": 2,
                            "From": [
                              {
                                "Name": "d",
                                "Entity": "DateAggregation",
                                "Type": 0
                              }
                            ],
                            "Where": [
                              {
                                "Condition": {
                                  "In": {
                                    "Expressions": [
                                      {
                                        "Column": {
                                          "Expression": {
                                            "SourceRef": {
                                              "Source": "d"
                                            }
                                          },
                                          "Property": "Date Aggregation"
                                        }
                                      }
                                    ],
                                    "Values": [
                                      [
                                        {
                                          "Literal": {
                                            "Value": "'None'"
                                          }
                                        }
                                      ]
                                    ]
                                  }
                                }
                              }
                            ]
                          }
                        }
                      }
                    }
                  ],
                  "data": [
                    {
                      "properties": {
                        "mode": {
                          "expr": {
                            "Literal": {
                              "Value": "'Dropdown'"
                            }
                          }
                        }
                      }
                    }
                  ],
                  "selection": [
                    {
                      "properties": {
                        "strictSingleSelect": {
                          "expr": {
                            "Literal": {
                              "Value": "true"
                            }
                          }
                        }
                      }
                    }
                  ]
                }
              },
              "activeProjections": {
                "Values": [
                  {
                    "Column": {
                      "Expression": {
                        "SourceRef": {
                          "Entity": "DateAggregation"
                        }
                      },
                      "Property": "Date Aggregation"
                    }
                  }
                ]
              },
              "display": {
                "mode": "hidden"
              }
            }
          },
          "b4ec5de1d8476c1cc142": {
            "filters": {
              "byExpr": [
                {
                  "name": "f5c68b3cced1959b7855",
                  "type": "Categorical",
                  "expression": {
                    "Column": {
                      "Expression": {
                        "SourceRef": {
                          "Entity": "DateAggregationTemporalFirst"
                        }
                      },
                      "Property": "Date Aggregation"
                    }
                  },
                  "howCreated": 0
                }
              ]
            },
            "singleVisual": {
              "visualType": "slicer",
              "objects": {
                "merge": {
                  "general": [
                    {
                      "properties": {
                        "filter": {
                          "filter": {
                            "Version": 2,
                            "From": [
                              {
                                "Name": "d",
                                "Entity": "DateAggregationTemporalFirst",
                                "Type": 0
                              }
                            ],
                            "Where": [
                              {
                                "Condition": {
                                  "In": {
                                    "Expressions": [
                                      {
                                        "Column": {
                                          "Expression": {
                                            "SourceRef": {
                                              "Source": "d"
                                            }
                                          },
                                          "Property": "Date Aggregation"
                                        }
                                      }
                                    ],
                                    "Values": [
                                      [
                                        {
                                          "Literal": {
                                            "Value": "'None'"
                                          }
                                        }
                                      ]
                                    ]
                                  }
                                }
                              }
                            ]
                          }
                        }
                      }
                    }
                  ],
                  "data": [
                    {
                      "properties": {
                        "mode": {
                          "expr": {
                            "Literal": {
                              "Value": "'Dropdown'"
                            }
                          }
                        }
                      }
                    }
                  ],
                  "selection": [
                    {
                      "properties": {
                        "strictSingleSelect": {
                          "expr": {
                            "Literal": {
                              "Value": "true"
                            }
                          }
                        }
                      }
                    }
                  ]
                }
              },
              "activeProjections": {
                "Values": [
                  {
                    "Column": {
                      "Expression": {
                        "SourceRef": {
                          "Entity": "DateAggregationTemporalFirst"
                        }
                      },
                      "Property": "Date Aggregation"
                    }
                  }
                ]
              }
            }
          },
          "ba13c66ee07617c6005d": {
            "filters": {
              "byExpr": [
                {
                  "name": "fbf3eaefd8b3d589ad64",
                  "type": "Categorical",
                  "expression": {
                    "Column": {
                      "Expression": {
                        "SourceRef": {
                          "Entity": "WeatherIndexAggregationTemporalFirst"
                        }
                      },
                      "Property": "Weather Index Aggregation"
                    }
                  },
                  "howCreated": 0
                }
              ]
            },
            "singleVisual": {
              "visualType": "slicer",
              "objects": {
                "merge": {
                  "general": [
                    {
                      "properties": {
                        "filter": {
                          "filter": {
                            "Version": 2,
                            "From": [
                              {
                                "Name": "w",
                                "Entity": "WeatherIndexAggregationTemporalFirst",
                                "Type": 0
                              }
                            ],
                            "Where": [
                              {
                                "Condition": {
                                  "In": {
                                    "Expressions": [
                                      {
                                        "Column": {
                                          "Expression": {
                                            "SourceRef": {
                                              "Source": "w"
                                            }
                                          },
                                          "Property": "Weather Index Aggregation"
                                        }
                                      }
                                    ],
                                    "Values": [
                                      [
                                        {
                                          "Literal": {
                                            "Value": "'None'"
                                          }
                                        }
                                      ]
                                    ]
                                  }
                                }
                              }
                            ]
                          }
                        }
                      }
                    }
                  ],
                  "data": [
                    {
                      "properties": {
                        "mode": {
                          "expr": {
                            "Literal": {
                              "Value": "'Dropdown'"
                            }
                          }
                        }
                      }
                    }
                  ],
                  "selection": [
                    {
                      "properties": {
                        "strictSingleSelect": {
                          "expr": {
                            "Literal": {
                              "Value": "true"
                            }
                          }
                        }
                      }
                    }
                  ]
                }
              },
              "activeProjections": {
                "Values": [
                  {
                    "Column": {
                      "Expression": {
                        "SourceRef": {
                          "Entity": "WeatherIndexAggregationTemporalFirst"
                        }
                      },
                      "Property": "Weather Index Aggregation"
                    }
                  }
                ]
              }
            }
          },
          "6ef62e4dc78b970684bf": {
            "filters": {
              "byExpr": [
                {
                  "name": "c78670098c9d97d98348",
                  "type": "Advanced",
                  "expression": {
                    "HierarchyLevel": {
                      "Expression": {
                        "Hierarchy": {
                          "Expression": {
                            "SourceRef": {
                              "Entity": "D_Date"
                            }
                          },
                          "Hierarchy": "DayOfMonth Hierarchy"
                        }
                      },
                      "Level": "Year"
                    }
                  },
                  "howCreated": 0
                },
                {
                  "name": "3f8688914e91897df9a1",
                  "type": "Categorical",
                  "expression": {
                    "HierarchyLevel": {
                      "Expression": {
                        "Hierarchy": {
                          "Expression": {
                            "SourceRef": {
                              "Entity": "D_Date"
                            }
                          },
                          "Hierarchy": "DayOfMonth Hierarchy"
                        }
                      },
                      "Level": "Quarter"
                    }
                  },
                  "howCreated": 0
                },
                {
                  "name": "af0ace90c787cd2cca1e",
                  "type": "Categorical",
                  "expression": {
                    "HierarchyLevel": {
                      "Expression": {
                        "Hierarchy": {
                          "Expression": {
                            "SourceRef": {
                              "Entity": "D_Date"
                            }
                          },
                          "Hierarchy": "DayOfMonth Hierarchy"
                        }
                      },
                      "Level": "MonthShort"
                    }
                  },
                  "howCreated": 0
                },
                {
                  "name": "c7bd977bafb9055541e6",
                  "type": "Advanced",
                  "expression": {
                    "HierarchyLevel": {
                      "Expression": {
                        "Hierarchy": {
                          "Expression": {
                            "SourceRef": {
                              "Entity": "D_Date"
                            }
                          },
                          "Hierarchy": "DayOfMonth Hierarchy"
                        }
                      },
                      "Level": "Day of Month"
                    }
                  },
                  "howCreated": 0
                },
                {
                  "name": "537f87e968724eb9d7e7",
                  "type": "Categorical",
                  "expression": {
                    "Column": {
                      "Expression": {
                        "SourceRef": {
                          "Entity": "D_Time"
                        }
                      },
                      "Property": "HourLabel"
                    }
                  },
                  "howCreated": 0
                },
                {
                  "name": "2e2f5f7fe05109d195e4",
                  "type": "Categorical",
                  "expression": {
                    "Column": {
                      "Expression": {
                        "SourceRef": {
                          "Entity": "D_Salesperson"
                        }
                      },
                      "Property": "Name"
                    }
                  },
                  "howCreated": 0
                },
                {
                  "name": "ae148131d25c49b8c1d2",
                  "type": "Advanced",
                  "expression": {
                    "Measure": {
                      "Expression": {
                        "SourceRef": {
                          "Entity": "Main_Measures"
                        }
                      },
                      "Property": "Sales Aggregation"
                    }
                  },
                  "howCreated": 0
                }
              ]
            },
            "singleVisual": {
              "visualType": "ribbonChart",
              "objects": {},
              "activeProjections": {
                "Category": [
                  {
                    "HierarchyLevel": {
                      "Expression": {
                        "Hierarchy": {
                          "Expression": {
                            "SourceRef": {
                              "Entity": "D_Date"
                            }
                          },
                          "Hierarchy": "DayOfMonth Hierarchy"
                        }
                      },
                      "Level": "Year"
                    }
                  },
                  {
                    "HierarchyLevel": {
                      "Expression": {
                        "Hierarchy": {
                          "Expression": {
                            "SourceRef": {
                              "Entity": "D_Date"
                            }
                          },
                          "Hierarchy": "DayOfMonth Hierarchy"
                        }
                      },
                      "Level": "Quarter"
                    }
                  },
                  {
                    "HierarchyLevel": {
                      "Expression": {
                        "Hierarchy": {
                          "Expression": {
                            "SourceRef": {
                              "Entity": "D_Date"
                            }
                          },
                          "Hierarchy": "DayOfMonth Hierarchy"
                        }
                      },
                      "Level": "MonthShort"
                    }
                  },
                  {
                    "HierarchyLevel": {
                      "Expression": {
                        "Hierarchy": {
                          "Expression": {
                            "SourceRef": {
                              "Entity": "D_Date"
                            }
                          },
                          "Hierarchy": "DayOfMonth Hierarchy"
                        }
                      },
                      "Level": "Day of Month"
                    }
                  }
                ]
              }
            }
          },
          "78dae74529a96b9179e6": {
            "filters": {
              "byExpr": [
                {
                  "name": "059e182f0515a5eaca4a",
                  "type": "Advanced",
                  "expression": {
                    "Measure": {
                      "Expression": {
                        "SourceRef": {
                          "Entity": "Main_Measures"
                        }
                      },
                      "Property": "Sales Aggregation Current To Previous Year"
                    }
                  },
                  "howCreated": 0
                },
                {
                  "name": "90c8aa8b74b0f2263e39",
                  "type": "Advanced",
                  "expression": {
                    "Measure": {
                      "Expression": {
                        "SourceRef": {
                          "Entity": "Main_Measures"
                        }
                      },
                      "Property": "Sales Aggregation Current Year"
                    }
                  },
                  "howCreated": 0
                }
              ]
            },
            "singleVisual": {
              "visualType": "gauge",
              "objects": {},
              "orderBy": [
                {
                  "Direction": 2,
                  "Expression": {
                    "Measure": {
                      "Expression": {
                        "SourceRef": {
                          "Entity": "Main_Measures"
                        }
                      },
                      "Property": "Sales Aggregation Current Year"
                    }
                  }
                }
              ]
            }
          },
          "13e03f5647e73183bd83": {
            "singleVisual": {
              "visualType": "actionButton",
              "objects": {}
            }
          },
          "3d6f51fbac19d8c993d1": {
            "singleVisual": {
              "visualType": "textbox",
              "objects": {}
            }
          },
          "50396b4dfeb8df49785e": {
            "filters": {
              "byExpr": [
                {
                  "name": "7c5b8b27a4829ad6a91a",
                  "type": "Categorical",
                  "expression": {
                    "Column": {
                      "Expression": {
                        "SourceRef": {
                          "Entity": "Use Full Axis"
                        }
                      },
                      "Property": "Use Full Axis"
                    }
                  },
                  "howCreated": 0
                }
              ]
            },
            "singleVisual": {
              "visualType": "slicer",
              "objects": {
                "merge": {
                  "data": [
                    {
                      "properties": {
                        "mode": {
                          "expr": {
                            "Literal": {
                              "Value": "'Basic'"
                            }
                          }
                        }
                      }
                    }
                  ]
                }
              },
              "activeProjections": {
                "Values": [
                  {
                    "Column": {
                      "Expression": {
                        "SourceRef": {
                          "Entity": "Use Full Axis"
                        }
                      },
                      "Property": "Use Full Axis"
                    }
                  }
                ]
              }
            }
          },
          "69be06cc2ba531cf8f08": {
            "filters": {
              "byExpr": [
                {
                  "name": "372c2e8e60c74e180b83",
                  "type": "Categorical",
                  "expression": {
                    "Column": {
                      "Expression": {
                        "SourceRef": {
                          "Entity": "Location Common Open Days"
                        }
                      },
                      "Property": "Calculation group column"
                    }
                  },
                  "howCreated": 0
                }
              ]
            },
            "singleVisual": {
              "visualType": "slicer",
              "objects": {
                "merge": {
                  "data": [
                    {
                      "properties": {
                        "mode": {
                          "expr": {
                            "Literal": {
                              "Value": "'Basic'"
                            }
                          }
                        }
                      }
                    }
                  ]
                }
              },
              "activeProjections": {
                "Values": [
                  {
                    "Column": {
                      "Expression": {
                        "SourceRef": {
                          "Entity": "Location Common Open Days"
                        }
                      },
                      "Property": "Calculation group column"
                    }
                  }
                ]
              }
            }
          },
          "cdb1e11000a9bca63fcd": {
            "filters": {
              "byExpr": [
                {
                  "name": "a21f037df7de4095d8ed",
                  "type": "Categorical",
                  "expression": {
                    "Column": {
                      "Expression": {
                        "SourceRef": {
                          "Entity": "Location Common Open Hours"
                        }
                      },
                      "Property": "Calculation group column"
                    }
                  },
                  "howCreated": 0
                }
              ]
            },
            "singleVisual": {
              "visualType": "slicer",
              "objects": {
                "merge": {
                  "data": [
                    {
                      "properties": {
                        "mode": {
                          "expr": {
                            "Literal": {
                              "Value": "'Basic'"
                            }
                          }
                        }
                      }
                    }
                  ]
                }
              },
              "activeProjections": {
                "Values": [
                  {
                    "Column": {
                      "Expression": {
                        "SourceRef": {
                          "Entity": "Location Common Open Hours"
                        }
                      },
                      "Property": "Calculation group column"
                    }
                  }
                ]
              }
            }
          },
          "e6cbd9b5f9e143d22782": {
            "filters": {
              "byExpr": [
                {
                  "name": "7d02d050beccd05bc4b3",
                  "type": "Advanced",
                  "expression": {
                    "Measure": {
                      "Expression": {
                        "SourceRef": {
                          "Entity": "Main_Measures"
                        }
                      },
                      "Property": "Sales Aggregation Yearly Average Previous Years"
                    }
                  },
                  "howCreated": 0
                },
                {
                  "name": "e3b5af7df0b0e2ff3044",
                  "type": "Advanced",
                  "expression": {
                    "Measure": {
                      "Expression": {
                        "SourceRef": {
                          "Entity": "Main_Measures"
                        }
                      },
                      "Property": "Sales Aggregation Current Year"
                    }
                  },
                  "howCreated": 0
                }
              ]
            },
            "singleVisual": {
              "visualType": "gauge",
              "objects": {},
              "orderBy": [
                {
                  "Direction": 2,
                  "Expression": {
                    "Measure": {
                      "Expression": {
                        "SourceRef": {
                          "Entity": "Main_Measures"
                        }
                      },
                      "Property": "Sales Aggregation Current Year"
                    }
                  }
                }
              ]
            }
          },
          "f99107cba0b315bc19ff": {
            "filters": {
              "byExpr": [
                {
                  "name": "a39021d158a3b79b9d91",
                  "type": "Advanced",
                  "filter": {
                    "Version": 2,
                    "From": [
                      {
                        "Name": "d",
                        "Entity": "DailyMeasureDefinitions",
                        "Type": 0
                      },
                      {
                        "Name": "m",
                        "Entity": "Main_Measures",
                        "Type": 0
                      }
                    ],
                    "Where": [
                      {
                        "Condition": {
                          "Comparison": {
                            "ComparisonKind": 0,
                            "Left": {
                              "Measure": {
                                "Expression": {
                                  "SourceRef": {
                                    "Source": "m"
                                  }
                                },
                                "Property": "Sum Daily Sales Aggregation Is Not Blank"
                              }
                            },
                            "Right": {
                              "Literal": {
                                "Value": "1L"
                              }
                            }
                          }
                        }
                      }
                    ]
                  },
                  "expression": {
                    "Measure": {
                      "Expression": {
                        "SourceRef": {
                          "Entity": "Main_Measures"
                        }
                      },
                      "Property": "Sum Daily Sales Aggregation Is Not Blank"
                    }
                  },
                  "howCreated": 1
                },
                {
                  "name": "f98d87a51480f103d2e3",
                  "type": "Advanced",
                  "expression": {
                    "Column": {
                      "Expression": {
                        "SourceRef": {
                          "Entity": "D_Date"
                        }
                      },
                      "Property": "Year"
                    }
                  },
                  "howCreated": 0
                },
                {
                  "name": "389c5a1b3f8529c2e0a9",
                  "type": "Advanced",
                  "expression": {
                    "Measure": {
                      "Expression": {
                        "SourceRef": {
                          "Entity": "Main_Measures"
                        }
                      },
                      "Property": "Sales Aggregation"
                    }
                  },
                  "howCreated": 0
                },
                {
                  "name": "773d6aae392185b00ade",
                  "type": "Advanced",
                  "expression": {
                    "Measure": {
                      "Expression": {
                        "SourceRef": {
                          "Entity": "Main_Measures"
                        }
                      },
                      "Property": "Sum Daily Sales Change Over Period Relative"
                    }
                  },
                  "howCreated": 0
                }
              ]
            },
            "singleVisual": {
              "visualType": "pivotTable",
              "objects": {},
              "activeProjections": {
                "Rows": [
                  {
                    "Column": {
                      "Expression": {
                        "SourceRef": {
                          "Entity": "D_Date"
                        }
                      },
                      "Property": "Year"
                    }
                  }
                ]
              },
              "expansionStates": [
                {
                  "roles": [
                    "Rows"
                  ],
                  "levels": [
                    {
                      "queryRefs": [
                        "DateTable.Year"
                      ],
                      "isCollapsed": true,
                      "identityKeys": [
                        {
                          "Column": {
                            "Expression": {
                              "SourceRef": {
                                "Entity": "DateTable"
                              }
                            },
                            "Property": "Year"
                          }
                        }
                      ],
                      "isPinned": true
                    }
                  ],
                  "root": {
                    "identityValues": [],
                    "children": [
                      {
                        "identityValues": [
                          {
                            "Literal": {
                              "Value": "2023L"
                            }
                          }
                        ],
                        "isToggled": true
                      }
                    ]
                  }
                }
              ]
            }
          },
          "fdd42d4e24b79cee7c88": {
            "filters": {
              "byExpr": [
                {
                  "name": "03d55302d944de2413eb",
                  "type": "Categorical",
                  "expression": {
                    "Column": {
                      "Expression": {
                        "SourceRef": {
                          "Entity": "D_Product_Category"
                        }
                      },
                      "Property": "category_name"
                    }
                  },
                  "howCreated": 0
                },
                {
                  "name": "3a292dc99e06958789ad",
                  "type": "Categorical",
                  "expression": {
                    "Column": {
                      "Expression": {
                        "SourceRef": {
                          "Entity": "D_Product"
                        }
                      },
                      "Property": "Product"
                    }
                  },
                  "howCreated": 0
                },
                {
                  "name": "d6fc78eaf96025be73da",
                  "type": "Advanced",
                  "expression": {
                    "Measure": {
                      "Expression": {
                        "SourceRef": {
                          "Entity": "Main_Measures"
                        }
                      },
                      "Property": "Sales Aggregation"
                    }
                  },
                  "howCreated": 0
                }
              ]
            },
            "singleVisual": {
              "visualType": "pivotTable",
              "objects": {},
              "orderBy": [
                {
                  "Direction": 2,
                  "Expression": {
                    "Column": {
                      "Expression": {
                        "SourceRef": {
                          "Entity": "D_Product"
                        }
                      },
                      "Property": "Product"
                    }
                  }
                }
              ],
              "activeProjections": {
                "Rows": [
                  {
                    "Column": {
                      "Expression": {
                        "SourceRef": {
                          "Entity": "D_Product_Category"
                        }
                      },
                      "Property": "category_name"
                    }
                  },
                  {
                    "Column": {
                      "Expression": {
                        "SourceRef": {
                          "Entity": "D_Product"
                        }
                      },
                      "Property": "Product"
                    }
                  }
                ]
              },
              "expansionStates": [
                {
                  "roles": [
                    "Rows"
                  ],
                  "levels": [
                    {
                      "queryRefs": [
                        "product_category_data.category_name"
                      ],
                      "isCollapsed": true,
                      "identityKeys": [
                        {
                          "Column": {
                            "Expression": {
                              "SourceRef": {
                                "Entity": "Product Category"
                              }
                            },
                            "Property": "category_name"
                          }
                        }
                      ],
                      "isPinned": true
                    },
                    {
                      "queryRefs": [
                        "product_data.product_name"
                      ],
                      "isCollapsed": true,
                      "isPinned": true
                    }
                  ],
                  "root": {
                    "identityValues": [],
                    "children": [
                      {
                        "identityValues": [
                          {
                            "Literal": {
                              "Value": "'Jaatelo'"
                            }
                          }
                        ],
                        "isToggled": true
                      }
                    ]
                  }
                }
              ]
            }
          },
          "e3d7c8e4a02fd90cebd4": {
            "filters": {
              "byExpr": [
                {
                  "name": "bdfee4a67c2e978d986d",
                  "type": "Advanced",
                  "expression": {
                    "Measure": {
                      "Expression": {
                        "SourceRef": {
                          "Entity": "Main_Measures"
                        }
                      },
                      "Property": "Sales Aggregation"
                    }
                  },
                  "howCreated": 0
                },
                {
                  "name": "d8f45aacf60679991877",
                  "type": "Advanced",
                  "expression": {
                    "Measure": {
                      "Expression": {
                        "SourceRef": {
                          "Entity": "Main_Measures"
                        }
                      },
                      "Property": "Location Rank"
                    }
                  },
                  "howCreated": 0
                }
              ]
            },
            "singleVisual": {
              "visualType": "cardVisual",
              "objects": {},
              "orderBy": [
                {
                  "Direction": 2,
                  "Expression": {
                    "Measure": {
                      "Expression": {
                        "SourceRef": {
                          "Entity": "Main_Measures"
                        }
                      },
                      "Property": "Sales Aggregation"
                    }
                  }
                }
              ]
            }
          }
        }
      }
    },
    "objects": {
      "merge": {
        "outspacePane": [
          {
            "properties": {
              "expanded": {
                "expr": {
                  "Literal": {
                    "Value": "false"
                  }
                }
              }
            }
          }
        ]
      }
    }
  }
}