{
  "$schema": "https://developer.microsoft.com/json-schemas/fabric/item/report/definition/visualContainer/2.4.0/schema.json",
  "name": "54811de72c04e742c383",
  "position": {
    "x": 6.3314097279472383,
    "y": 346.11706512778238,
    "z": 9000,
    "height": 192.05276174773289,
    "width": 181.50041220115418,
    "tabOrder": 9000
  },
  "visual": {
    "visualType": "gauge",
    "query": {
      "queryState": {
        "TargetValue": {
          "projections": [
            {
              "field": {
                "Measure": {
                  "Expression": {
                    "SourceRef": {
                      "Entity": "Main_Measures"
                    }
                  },
                  "Property": "Sales Aggregation Yearly Average Previous Years"
                }
              },
              "queryRef": "HourlyMeasureDefinitions.Sales Aggregation Yearly Average Previous Years",
              "nativeQueryRef": "Sales Aggregation Yearly Average Previous Years"
            }
          ]
        },
        "Y": {
          "projections": [
            {
              "field": {
                "Measure": {
                  "Expression": {
                    "SourceRef": {
                      "Entity": "Main_Measures"
                    }
                  },
                  "Property": "Sales Aggregation Current Year"
                }
              },
              "queryRef": "HourlyMeasureDefinitions.Sales Aggregation Current Year",
              "nativeQueryRef": "Sales Aggregation Current Year"
            }
          ]
        }
      },
      "sortDefinition": {
        "sort": [
          {
            "field": {
              "Measure": {
                "Expression": {
                  "SourceRef": {
                    "Entity": "Main_Measures"
                  }
                },
                "Property": "Sales Aggregation Current Year"
              }
            },
            "direction": "Descending"
          }
        ],
        "isDefaultSort": true
      }
    },
    "objects": {
      "labels": [
        {
          "properties": {
            "show": {
              "expr": {
                "Literal": {
                  "Value": "true"
                }
              }
            }
          }
        }
      ],
      "target": [
        {
          "properties": {
            "show": {
              "expr": {
                "Literal": {
                  "Value": "true"
                }
              }
            }
          }
        }
      ],
      "calloutValue": [
        {
          "properties": {
            "show": {
              "expr": {
                "Literal": {
                  "Value": "true"
                }
              }
            }
          }
        }
      ]
    },
    "visualContainerObjects": {
      "title": [
        {
          "properties": {
            "text": {
              "expr": {
                "Literal": {
                  "Value": "'Current year vs historical average of Sales Aggregation'"
                }
              }
            },
            "fontSize": {
              "expr": {
                "Literal": {
                  "Value": "11D"
                }
              }
            },
            "alignment": {
              "expr": {
                "Literal": {
                  "Value": "'center'"
                }
              }
            }
          }
        }
      ]
    },
    "drillFilterOtherVisuals": true
  }
}